MANIFEST.in
README.rst
setup.py
py2loggly/__init__.py
py2loggly/cli.py
py2loggly/formatter.py
py2loggly/server.py
py2loggly.egg-info/PKG-INFO
py2loggly.egg-info/SOURCES.txt
py2loggly.egg-info/dependency_links.txt
py2loggly.egg-info/entry_points.txt
py2loggly.egg-info/not-zip-safe
py2loggly.egg-info/pbr.json
py2loggly.egg-info/requires.txt
py2loggly.egg-info/top_level.txt