Metadata-Version: 1.1
Name: py2loggly
Version: 1.1.2
Summary: A proxy for python UDP/TCP logging to loggly
Home-page: https://github.com/sebest/py2loggly
Author: Sebastien Estienne
Author-email: sebastien.estienne@gmail.com
License: MIT
Keywords: loggly,logging
Platform: UNKNOWN
Classifier: Development Status :: 5 - Production/Stable
Classifier: Intended Audience :: System Administrators
Classifier: License :: OSI Approved :: MIT License
Classifier: Natural Language :: English
Classifier: Programming Language :: Python :: 2
Classifier: Programming Language :: Python :: 2.7
Classifier: Programming Language :: Python :: 3
Classifier: Programming Language :: Python :: 3.3
